eclipse_zenoh-1.7.2.dist-info/METADATA
eclipse_zenoh-1.7.2.dist-info/WHEEL
eclipse_zenoh-1.7.2.dist-info/licenses/LICENSE
eclipse_zenoh-1.7.2.dist-info/licenses/NOTICE.md
zenoh/__init__.py
zenoh/__init__.pyi
zenoh/ext.py
zenoh/ext.pyi
zenoh/handlers.pyi
zenoh/py.typed
zenoh/shm.py
zenoh/shm.pyi
zenoh/zenoh.abi3.so
eclipse_zenoh-1.7.2.dist-info/RECORD
