Metadata-Version: 2.4
Name: eclipse-zenoh
Version: 1.7.2
Classifier: Programming Language :: Python :: 3 :: Only
Classifier: Programming Language :: Python :: 3.8
Classifier: Programming Language :: Python :: 3.9
Classifier: Programming Language :: Python :: 3.10
Classifier: Programming Language :: Python :: 3.11
Classifier: Programming Language :: Python :: 3.12
Classifier: Programming Language :: Rust
Classifier: Intended Audience :: Developers
Classifier: Development Status :: 4 - Beta
Classifier: Topic :: System :: Networking
Classifier: License :: OSI Approved :: Apache Software License
Classifier: License :: OSI Approved :: Eclipse Public License 2.0 (EPL-2.0)
Classifier: Operating System :: POSIX :: Linux
Classifier: Operating System :: MacOS :: MacOS X
Classifier: Operating System :: Microsoft :: Windows
License-File: LICENSE
License-File: NOTICE.md
Summary: The Zenoh Python API
Author: kydos <angelo@icorsaro.net>, Julien Enoch <julien@enoch.fr>, Olivier Hécart <olivier.hecart@adlinktech.com>, Luca Cominardi <luca.cominardi@gmail.com>, Pierre Avital <pierre.avital@adlinktech.com>
Author-email: kydos <angelo@icorsaro.net>, Julien Enoch <julien@enoch.fr>, Olivier Hécart <olivier.hecart@adlinktech.com>, Luca Cominardi <luca.cominardi@gmail.com>, Pierre Avital <pierre.avital@adlinktech.com>
Requires-Python: >=3.8
Project-URL: Bug Tracker, https://github.com/eclipse-zenoh/zenoh-python/issues
Project-URL: Documentation, https://readthedocs.org/projects/zenoh-python/
Project-URL: Source Code, https://github.com/eclipse-zenoh/zenoh-python
